allgoget/__init__.py
allgoget/data/__init__.py
allgoget/data/_rates.py
allgoget/utils/__init__.py
allgoget/utils/_utils.py
AllGoGet-0.0.1.dist-info/LICENSE
AllGoGet-0.0.1.dist-info/METADATA
AllGoGet-0.0.1.dist-info/WHEEL
AllGoGet-0.0.1.dist-info/top_level.txt
AllGoGet-0.0.1.dist-info/RECORD
